{
  "nodes": {
    "before-first": { "text": "Before first" },
    "first-a": { "text": "First A" },
    "first-b": { "text": "First B" },
    "second-a": { "text": "Second A" },
    "second-b": { "text": "Second B" },
    "second-c": { "text": "Second C" },
    "in-between-second": { "text": "In between second" },
    "third-1": { "text": "Third 1" },
    "third-2": { "text": "Third 2" },
    "third-3": { "text": "Third 3" },
    "third-4": { "text": "Third 4" },
    "fourth-a": { "text": "Fourth A?" },
    "fourth-b": { "text": "Fourth B?" },
    "you-said-no": { "text": "You said No" },
    "you-said-yes": { "text": "You said Yes" },
    "thats-it": { "text": "That's it!" }
  },
  "edges": [
    { "from": "before-first", "to": "first-a"},
    { "from": "before-first", "to": "first-b"},
    { "from": "first-a", "to": "second-a", "text": "Yes" },
    { "from": "first-a", "to": "second-b", "text": "No"},
    { "from": "first-b", "to": "second-c" },
    { "from": "second-a", "to": "in-between-second" },
    { "from": "second-b", "to": "in-between-second", "text": "Go straight" },
    { "from": "in-between-second", "to": "third-1" },
    { "from": "in-between-second", "to": "third-2" },
    { "from": "in-between-second", "to": "third-3" },
    { "from": "in-between-second", "to": "third-4" },
    { "from": "third-1", "to": "fourth-a" },
    { "from": "third-2", "to": "fourth-a" },
    { "from": "third-3", "to": "fourth-b" },
    { "from": "third-4", "to": "fourth-b" },
    { "from": "fourth-a", "to": "you-said-no" },
    { "from": "fourth-a", "to": "you-said-yes" },
    { "from": "fourth-b", "to": "you-said-no" },
    { "from": "fourth-b", "to": "you-said-yes" },
    { "from": "fourth-b", "to": "third-3", "text": "Go back" },
    { "from": "fourth-b", "to": "third-4", "text": "Detour" },
    { "from": "fourth-a", "to": "third-1" },
    { "from": "fourth-b", "to": "second-c" },
    { "from": "fourth-a", "to": "second-a", "text": "Go back" },
    { "from": "fourth-a", "to": "third-2", "text": "Turn around" },
    { "from": "you-said-no", "to": "thats-it" },
    { "from": "you-said-yes", "to": "thats-it" }
  ]
}
